django_invoice2-0.1.1.dist-info/DESCRIPTION.rst
django_invoice2-0.1.1.dist-info/METADATA
django_invoice2-0.1.1.dist-info/RECORD
django_invoice2-0.1.1.dist-info/WHEEL
django_invoice2-0.1.1.dist-info/metadata.json
django_invoice2-0.1.1.dist-info/top_level.txt
invoice/__init__.py
invoice/admin.py
invoice/models.py
invoice/tests.py
invoice/urls.py
invoice/views.py
invoice/exports/__init__.py
invoice/exports/html.py
invoice/exports/pdf.py
invoice/locale/cs/LC_MESSAGES/django.mo
invoice/locale/cs/LC_MESSAGES/django.po
invoice/migrations/0001_initial.py
invoice/migrations/__init__.py
invoice/static/invoice/FreeSans.ttf
invoice/templates/admin/invoice/invoice/change_form.html
invoice/templates/invoice/invoice.html
invoice/templatetags/__init__.py
invoice/templatetags/invoice.py
invoice/utils/__init__.py
