Metadata-Version: 2.0
Name: django-invoice2
Version: 0.1.1
Summary: Pluggable django invoicing app
Home-page: https://github.com/katomaso/django-invoice
Author: Tomas Peterka
Author-email: prestizni@gmail.com
License: MIT
Keywords: django invoice pdf
Platform: UNKNOWN
Requires-Dist: django (>=1.8)
Requires-Dist: reportlab
